<?xml version="1.0" encoding="UTF-8"?>
<spirit:abstractionDefinition xmlns:xilinx="http://www.xilinx.com" xmlns:spirit="http://www.spiritconsortium.org/XMLSchema/SPIRIT/1685-2009" xmlns:xsi="http://www.w3.org/2001/XMLSchema-instance">
  <spirit:vendor>th-nuernberg.de</spirit:vendor>
  <spirit:library>user</spirit:library>
  <spirit:name>uz_inverter_adapter_rtl</spirit:name>
  <spirit:version>1.0</spirit:version>
  <spirit:busType spirit:vendor="th-nuernberg.de" spirit:library="user" spirit:name="uz_inverter_adapter" spirit:version="1.0"/>
  <spirit:ports>
    <spirit:port>
      <spirit:logicalName>pwm_h1</spirit:logicalName>
      <spirit:description>gate h1</spirit:description>
      <spirit:wire>
        <spirit:onMaster>
          <spirit:presence>required</spirit:presence>
          <spirit:width>1</spirit:width>
        </spirit:onMaster>
        <spirit:onSlave>
          <spirit:presence>required</spirit:presence>
          <spirit:width>1</spirit:width>
          <spirit:direction>in</spirit:direction>
        </spirit:onSlave>
        <spirit:defaultValue>0</spirit:defaultValue>
      </spirit:wire>
    </spirit:port>
    <spirit:port>
      <spirit:logicalName>pwm_l1</spirit:logicalName>
      <spirit:description>gate l1</spirit:description>
      <spirit:wire>
        <spirit:onMaster>
          <spirit:presence>required</spirit:presence>
          <spirit:width>1</spirit:width>
        </spirit:onMaster>
        <spirit:onSlave>
          <spirit:presence>required</spirit:presence>
          <spirit:width>1</spirit:width>
          <spirit:direction>in</spirit:direction>
        </spirit:onSlave>
        <spirit:defaultValue>0</spirit:defaultValue>
      </spirit:wire>
    </spirit:port>
    <spirit:port>
      <spirit:logicalName>pwm_h2</spirit:logicalName>
      <spirit:description>gate h2</spirit:description>
      <spirit:wire>
        <spirit:onMaster>
          <spirit:presence>required</spirit:presence>
          <spirit:width>1</spirit:width>
        </spirit:onMaster>
        <spirit:onSlave>
          <spirit:presence>required</spirit:presence>
          <spirit:width>1</spirit:width>
          <spirit:direction>in</spirit:direction>
        </spirit:onSlave>
        <spirit:defaultValue>0</spirit:defaultValue>
      </spirit:wire>
    </spirit:port>
    <spirit:port>
      <spirit:logicalName>pwm_l2</spirit:logicalName>
      <spirit:description>gate l2</spirit:description>
      <spirit:wire>
        <spirit:onMaster>
          <spirit:presence>required</spirit:presence>
          <spirit:width>1</spirit:width>
        </spirit:onMaster>
        <spirit:onSlave>
          <spirit:presence>required</spirit:presence>
          <spirit:width>1</spirit:width>
          <spirit:direction>in</spirit:direction>
        </spirit:onSlave>
        <spirit:defaultValue>0</spirit:defaultValue>
      </spirit:wire>
    </spirit:port>
    <spirit:port>
      <spirit:logicalName>pwm_h3</spirit:logicalName>
      <spirit:description>gate h3</spirit:description>
      <spirit:wire>
        <spirit:onMaster>
          <spirit:presence>required</spirit:presence>
          <spirit:width>1</spirit:width>
        </spirit:onMaster>
        <spirit:onSlave>
          <spirit:presence>required</spirit:presence>
          <spirit:width>1</spirit:width>
          <spirit:direction>in</spirit:direction>
        </spirit:onSlave>
        <spirit:defaultValue>0</spirit:defaultValue>
      </spirit:wire>
    </spirit:port>
    <spirit:port>
      <spirit:logicalName>pwm_l3</spirit:logicalName>
      <spirit:description>gate l3</spirit:description>
      <spirit:wire>
        <spirit:onMaster>
          <spirit:presence>required</spirit:presence>
          <spirit:width>1</spirit:width>
        </spirit:onMaster>
        <spirit:onSlave>
          <spirit:presence>required</spirit:presence>
          <spirit:width>1</spirit:width>
          <spirit:direction>in</spirit:direction>
        </spirit:onSlave>
        <spirit:defaultValue>0</spirit:defaultValue>
      </spirit:wire>
    </spirit:port>
    <spirit:port>
      <spirit:logicalName>i1_diag</spirit:logicalName>
      <spirit:description>i1_diag</spirit:description>
      <spirit:wire>
        <spirit:onMaster>
          <spirit:presence>required</spirit:presence>
          <spirit:width>1</spirit:width>
          <spirit:direction>in</spirit:direction>
        </spirit:onMaster>
        <spirit:onSlave>
          <spirit:presence>required</spirit:presence>
          <spirit:width>1</spirit:width>
        </spirit:onSlave>
        <spirit:defaultValue>0</spirit:defaultValue>
      </spirit:wire>
    </spirit:port>
    <spirit:port>
      <spirit:logicalName>h1_temp</spirit:logicalName>
      <spirit:description>h1_temp</spirit:description>
      <spirit:wire>
        <spirit:onMaster>
          <spirit:presence>required</spirit:presence>
          <spirit:width>1</spirit:width>
          <spirit:direction>in</spirit:direction>
        </spirit:onMaster>
        <spirit:onSlave>
          <spirit:presence>required</spirit:presence>
          <spirit:width>1</spirit:width>
        </spirit:onSlave>
        <spirit:defaultValue>0</spirit:defaultValue>
      </spirit:wire>
    </spirit:port>
    <spirit:port>
      <spirit:logicalName>i2_diag</spirit:logicalName>
      <spirit:description>i2_diag</spirit:description>
      <spirit:wire>
        <spirit:onMaster>
          <spirit:presence>required</spirit:presence>
          <spirit:width>1</spirit:width>
          <spirit:direction>in</spirit:direction>
        </spirit:onMaster>
        <spirit:onSlave>
          <spirit:presence>required</spirit:presence>
          <spirit:width>1</spirit:width>
        </spirit:onSlave>
        <spirit:defaultValue>0</spirit:defaultValue>
      </spirit:wire>
    </spirit:port>
    <spirit:port>
      <spirit:logicalName>l1_temp</spirit:logicalName>
      <spirit:description>l1_temp</spirit:description>
      <spirit:wire>
        <spirit:onMaster>
          <spirit:presence>required</spirit:presence>
          <spirit:width>1</spirit:width>
          <spirit:direction>in</spirit:direction>
        </spirit:onMaster>
        <spirit:onSlave>
          <spirit:presence>required</spirit:presence>
          <spirit:width>1</spirit:width>
        </spirit:onSlave>
        <spirit:defaultValue>0</spirit:defaultValue>
      </spirit:wire>
    </spirit:port>
    <spirit:port>
      <spirit:logicalName>i3_diag</spirit:logicalName>
      <spirit:description>i3_diag</spirit:description>
      <spirit:wire>
        <spirit:onMaster>
          <spirit:presence>required</spirit:presence>
          <spirit:width>1</spirit:width>
          <spirit:direction>in</spirit:direction>
        </spirit:onMaster>
        <spirit:onSlave>
          <spirit:presence>required</spirit:presence>
          <spirit:width>1</spirit:width>
        </spirit:onSlave>
        <spirit:defaultValue>0</spirit:defaultValue>
      </spirit:wire>
    </spirit:port>
    <spirit:port>
      <spirit:logicalName>l1_oc</spirit:logicalName>
      <spirit:description>l1_oc</spirit:description>
      <spirit:wire>
        <spirit:onMaster>
          <spirit:presence>required</spirit:presence>
          <spirit:width>1</spirit:width>
          <spirit:direction>in</spirit:direction>
        </spirit:onMaster>
        <spirit:onSlave>
          <spirit:presence>required</spirit:presence>
          <spirit:width>1</spirit:width>
        </spirit:onSlave>
        <spirit:defaultValue>0</spirit:defaultValue>
      </spirit:wire>
    </spirit:port>
    <spirit:port>
      <spirit:logicalName>i_diag</spirit:logicalName>
      <spirit:description>i_diag</spirit:description>
      <spirit:wire>
        <spirit:onMaster>
          <spirit:presence>required</spirit:presence>
          <spirit:width>1</spirit:width>
          <spirit:direction>in</spirit:direction>
        </spirit:onMaster>
        <spirit:onSlave>
          <spirit:presence>required</spirit:presence>
          <spirit:width>1</spirit:width>
        </spirit:onSlave>
        <spirit:defaultValue>0</spirit:defaultValue>
      </spirit:wire>
    </spirit:port>
    <spirit:port>
      <spirit:logicalName>l1_fault</spirit:logicalName>
      <spirit:description>l1_fault</spirit:description>
      <spirit:wire>
        <spirit:onMaster>
          <spirit:presence>required</spirit:presence>
          <spirit:width>1</spirit:width>
          <spirit:direction>in</spirit:direction>
        </spirit:onMaster>
        <spirit:onSlave>
          <spirit:presence>required</spirit:presence>
          <spirit:width>1</spirit:width>
        </spirit:onSlave>
        <spirit:defaultValue>0</spirit:defaultValue>
      </spirit:wire>
    </spirit:port>
    <spirit:port>
      <spirit:logicalName>pwm_en</spirit:logicalName>
      <spirit:description>pwm_en</spirit:description>
      <spirit:wire>
        <spirit:onMaster>
          <spirit:presence>required</spirit:presence>
          <spirit:width>1</spirit:width>
        </spirit:onMaster>
        <spirit:onSlave>
          <spirit:presence>required</spirit:presence>
          <spirit:width>1</spirit:width>
          <spirit:direction>in</spirit:direction>
        </spirit:onSlave>
        <spirit:defaultValue>0</spirit:defaultValue>
      </spirit:wire>
    </spirit:port>
    <spirit:port>
      <spirit:logicalName>h1_oc</spirit:logicalName>
      <spirit:description>h1_oc</spirit:description>
      <spirit:wire>
        <spirit:onMaster>
          <spirit:presence>required</spirit:presence>
          <spirit:width>1</spirit:width>
          <spirit:direction>in</spirit:direction>
        </spirit:onMaster>
        <spirit:onSlave>
          <spirit:presence>required</spirit:presence>
          <spirit:width>1</spirit:width>
        </spirit:onSlave>
        <spirit:defaultValue>0</spirit:defaultValue>
      </spirit:wire>
    </spirit:port>
    <spirit:port>
      <spirit:logicalName>DIG_IO_17</spirit:logicalName>
      <spirit:description>DIG_IO_17</spirit:description>
      <spirit:wire>
        <spirit:onMaster>
          <spirit:presence>required</spirit:presence>
          <spirit:width>1</spirit:width>
          <spirit:direction>in</spirit:direction>
        </spirit:onMaster>
        <spirit:onSlave>
          <spirit:presence>required</spirit:presence>
          <spirit:width>1</spirit:width>
        </spirit:onSlave>
        <spirit:defaultValue>0</spirit:defaultValue>
      </spirit:wire>
    </spirit:port>
    <spirit:port>
      <spirit:logicalName>h1_fault</spirit:logicalName>
      <spirit:description>h1_fault</spirit:description>
      <spirit:wire>
        <spirit:onMaster>
          <spirit:presence>required</spirit:presence>
          <spirit:width>1</spirit:width>
          <spirit:direction>in</spirit:direction>
        </spirit:onMaster>
        <spirit:onSlave>
          <spirit:presence>required</spirit:presence>
          <spirit:width>1</spirit:width>
        </spirit:onSlave>
        <spirit:defaultValue>0</spirit:defaultValue>
      </spirit:wire>
    </spirit:port>
    <spirit:port>
      <spirit:logicalName>h3_temp</spirit:logicalName>
      <spirit:description>h3_temp</spirit:description>
      <spirit:wire>
        <spirit:onMaster>
          <spirit:presence>required</spirit:presence>
          <spirit:width>1</spirit:width>
          <spirit:direction>in</spirit:direction>
        </spirit:onMaster>
        <spirit:onSlave>
          <spirit:presence>required</spirit:presence>
          <spirit:width>1</spirit:width>
        </spirit:onSlave>
        <spirit:defaultValue>0</spirit:defaultValue>
      </spirit:wire>
    </spirit:port>
    <spirit:port>
      <spirit:logicalName>h2_temp</spirit:logicalName>
      <spirit:description>h2_temp</spirit:description>
      <spirit:wire>
        <spirit:onMaster>
          <spirit:presence>required</spirit:presence>
          <spirit:width>1</spirit:width>
          <spirit:direction>in</spirit:direction>
        </spirit:onMaster>
        <spirit:onSlave>
          <spirit:presence>required</spirit:presence>
          <spirit:width>1</spirit:width>
        </spirit:onSlave>
        <spirit:defaultValue>0</spirit:defaultValue>
      </spirit:wire>
    </spirit:port>
    <spirit:port>
      <spirit:logicalName>l3_temp</spirit:logicalName>
      <spirit:description>l3_temp</spirit:description>
      <spirit:wire>
        <spirit:onMaster>
          <spirit:presence>required</spirit:presence>
          <spirit:width>1</spirit:width>
          <spirit:direction>in</spirit:direction>
        </spirit:onMaster>
        <spirit:onSlave>
          <spirit:presence>required</spirit:presence>
          <spirit:width>1</spirit:width>
        </spirit:onSlave>
        <spirit:defaultValue>0</spirit:defaultValue>
      </spirit:wire>
    </spirit:port>
    <spirit:port>
      <spirit:logicalName>l2_temp</spirit:logicalName>
      <spirit:description>l2_temp</spirit:description>
      <spirit:wire>
        <spirit:onMaster>
          <spirit:presence>required</spirit:presence>
          <spirit:width>1</spirit:width>
          <spirit:direction>in</spirit:direction>
        </spirit:onMaster>
        <spirit:onSlave>
          <spirit:presence>required</spirit:presence>
          <spirit:width>1</spirit:width>
        </spirit:onSlave>
        <spirit:defaultValue>0</spirit:defaultValue>
      </spirit:wire>
    </spirit:port>
    <spirit:port>
      <spirit:logicalName>l3_oc</spirit:logicalName>
      <spirit:description>l3_oc</spirit:description>
      <spirit:wire>
        <spirit:onMaster>
          <spirit:presence>required</spirit:presence>
          <spirit:width>1</spirit:width>
          <spirit:direction>in</spirit:direction>
        </spirit:onMaster>
        <spirit:onSlave>
          <spirit:presence>required</spirit:presence>
          <spirit:width>1</spirit:width>
        </spirit:onSlave>
        <spirit:defaultValue>0</spirit:defaultValue>
      </spirit:wire>
    </spirit:port>
    <spirit:port>
      <spirit:logicalName>l2_oc</spirit:logicalName>
      <spirit:description>l2_oc</spirit:description>
      <spirit:wire>
        <spirit:onMaster>
          <spirit:presence>required</spirit:presence>
          <spirit:width>1</spirit:width>
          <spirit:direction>in</spirit:direction>
        </spirit:onMaster>
        <spirit:onSlave>
          <spirit:presence>required</spirit:presence>
          <spirit:width>1</spirit:width>
        </spirit:onSlave>
        <spirit:defaultValue>0</spirit:defaultValue>
      </spirit:wire>
    </spirit:port>
    <spirit:port>
      <spirit:logicalName>l3_fault</spirit:logicalName>
      <spirit:description>l3_fault</spirit:description>
      <spirit:wire>
        <spirit:onMaster>
          <spirit:presence>required</spirit:presence>
          <spirit:width>1</spirit:width>
          <spirit:direction>in</spirit:direction>
        </spirit:onMaster>
        <spirit:onSlave>
          <spirit:presence>required</spirit:presence>
          <spirit:width>1</spirit:width>
        </spirit:onSlave>
        <spirit:defaultValue>0</spirit:defaultValue>
      </spirit:wire>
    </spirit:port>
    <spirit:port>
      <spirit:logicalName>l2_fault</spirit:logicalName>
      <spirit:description>l2_fault</spirit:description>
      <spirit:wire>
        <spirit:onMaster>
          <spirit:presence>required</spirit:presence>
          <spirit:width>1</spirit:width>
          <spirit:direction>in</spirit:direction>
        </spirit:onMaster>
        <spirit:onSlave>
          <spirit:presence>required</spirit:presence>
          <spirit:width>1</spirit:width>
        </spirit:onSlave>
        <spirit:defaultValue>0</spirit:defaultValue>
      </spirit:wire>
    </spirit:port>
    <spirit:port>
      <spirit:logicalName>h3_oc</spirit:logicalName>
      <spirit:description>h3_oc</spirit:description>
      <spirit:wire>
        <spirit:onMaster>
          <spirit:presence>required</spirit:presence>
          <spirit:width>1</spirit:width>
          <spirit:direction>in</spirit:direction>
        </spirit:onMaster>
        <spirit:onSlave>
          <spirit:presence>required</spirit:presence>
          <spirit:width>1</spirit:width>
        </spirit:onSlave>
        <spirit:defaultValue>0</spirit:defaultValue>
      </spirit:wire>
    </spirit:port>
    <spirit:port>
      <spirit:logicalName>h2_oc</spirit:logicalName>
      <spirit:description>h2_oc</spirit:description>
      <spirit:wire>
        <spirit:onMaster>
          <spirit:presence>required</spirit:presence>
          <spirit:width>1</spirit:width>
          <spirit:direction>in</spirit:direction>
        </spirit:onMaster>
        <spirit:onSlave>
          <spirit:presence>required</spirit:presence>
          <spirit:width>1</spirit:width>
        </spirit:onSlave>
        <spirit:defaultValue>0</spirit:defaultValue>
      </spirit:wire>
    </spirit:port>
    <spirit:port>
      <spirit:logicalName>h3_fault</spirit:logicalName>
      <spirit:description>h3_fault</spirit:description>
      <spirit:wire>
        <spirit:onMaster>
          <spirit:presence>required</spirit:presence>
          <spirit:width>1</spirit:width>
          <spirit:direction>in</spirit:direction>
        </spirit:onMaster>
        <spirit:onSlave>
          <spirit:presence>required</spirit:presence>
          <spirit:width>1</spirit:width>
        </spirit:onSlave>
        <spirit:defaultValue>0</spirit:defaultValue>
      </spirit:wire>
    </spirit:port>
    <spirit:port>
      <spirit:logicalName>h2_fault</spirit:logicalName>
      <spirit:description>h2_fault</spirit:description>
      <spirit:wire>
        <spirit:onMaster>
          <spirit:presence>required</spirit:presence>
          <spirit:width>1</spirit:width>
          <spirit:direction>in</spirit:direction>
        </spirit:onMaster>
        <spirit:onSlave>
          <spirit:presence>required</spirit:presence>
          <spirit:width>1</spirit:width>
        </spirit:onSlave>
        <spirit:defaultValue>0</spirit:defaultValue>
      </spirit:wire>
    </spirit:port>
  </spirit:ports>
  <spirit:vendorExtensions>
    <xilinx:abstractionDefinitionInfo>
      <xilinx:displayName>uz_inverter_adapter</xilinx:displayName>
    </xilinx:abstractionDefinitionInfo>
  </spirit:vendorExtensions>
</spirit:abstractionDefinition>
